zxj_portal_gun/__init__.py
zxj_portal_gun/__main__.py
zxj_portal_gun/main.py
zxj_portal_gun-0.2.0.dist-info/METADATA
zxj_portal_gun-0.2.0.dist-info/WHEEL
zxj_portal_gun-0.2.0.dist-info/entry_points.txt
zxj_portal_gun-0.2.0.dist-info/RECORD
