Metadata-Version: 2.1
Name: zxj-portal-gun
Version: 0.2.0
Summary: 
Author: xiaojian
Author-email: xiaojian.zhou@wabtec.com
Requires-Python: >=3.12,<4.0
Classifier: Programming Language :: Python :: 3
Classifier: Programming Language :: Python :: 3.12
Requires-Dist: typer[all] (>=0.12.3,<0.13.0)
